neuroskill/__init__.py
neuroskill-0.0.1.dist-info/METADATA
neuroskill-0.0.1.dist-info/WHEEL
neuroskill-0.0.1.dist-info/top_level.txt
neuroskill-0.0.1.dist-info/RECORD
