Metadata-Version: 2.1
Name: neuroskill
Version: 0.0.1
Summary: The neuroskill library.
Home-page: 
Author: liangyuan
Author-email: liangyuannnnn@gmail.com
Classifier: Programming Language :: Python :: 3
Classifier: License :: OSI Approved :: MIT License
Classifier: Operating System :: OS Independent
Requires-Python: >=3.6
